radon/__init__.py
radon/__main__.py
radon/cpl.py
radon/dp_ast.py
radon/error.py
radon/nbt_definitions.py
radon/tokenizer.py
radon/transpiler.py
radon/utils.py
radon/builtin/data.py
radon/builtin/exit.py
radon/builtin/getpos.py
radon/builtin/listener.py
radon/builtin/print.py
radon/builtin/pyeval.py
radon/builtin/raycast.py
radon/builtin/recipe.py
radon/builtin/rmath.py
radon/builtin/stdvar.py
radon/builtin/success.py
radon/builtin/swap.py
radon/builtin/time.py
radonmc-2.2.5.dist-info/METADATA
radonmc-2.2.5.dist-info/WHEEL
radonmc-2.2.5.dist-info/entry_points.txt
radonmc-2.2.5.dist-info/top_level.txt
radonmc-2.2.5.dist-info/RECORD
