Metadata-Version: 2.1
Name: radonmc
Version: 2.2.5
Summary: Radon is a programming language that gets compiled to Minecraft: Java Edition's mcfunction files.
Home-page: https://github.com/OguzhanUmutlu/radon
Author: OguzhanUmutlu
License: MIT
